servepy.py
servepy-1.0.3.dist-info/METADATA
servepy-1.0.3.dist-info/RECORD
servepy-1.0.3.dist-info/WHEEL
servepy-1.0.3.dist-info/top_level.txt
